BMDFO/SBDO.py
BMDFO/__init__.py
BMDFO/toy.py
BMMDO/SBJ.py
BMMDO/Sellar.py
BMMDO/__init__.py
NOBM-2404.2.dist-info/LICENSE
NOBM-2404.2.dist-info/METADATA
NOBM-2404.2.dist-info/WHEEL
NOBM-2404.2.dist-info/top_level.txt
NOBM-2404.2.dist-info/RECORD
